autopilot-0.3.0.dist-info/METADATA
autopilot-0.3.0.dist-info/metadata.json
autopilot-0.3.0.dist-info/DESCRIPTION.rst
autopilot-0.3.0.dist-info/RECORD
autopilot-0.3.0.dist-info/WHEEL
autopilot-0.3.0.dist-info/top_level.txt
autopilot-0.3.0.dist-info/entry_points.txt
autopilot/exceptions.py
autopilot/utils.py
autopilot/main.py
autopilot/validate.py
autopilot/ui.py
autopilot/git.py
autopilot/__init__.py
autopilot/render.py
autopilot/pypi.py
autopilot/data/default_config.yml
autopilot/data/license_list.txt
autopilot/data/licenses/Private
autopilot/data/licenses/GPLv2
autopilot/data/licenses/Apache
autopilot/data/licenses/MIT
autopilot/data/licenses/Mozilla
autopilot/data/licenses/GPLv3
autopilot/data/templates/setup.py
autopilot/data/templates/README.rst
autopilot/data/templates/setup.cfg
autopilot/data/templates/.travis.yml
autopilot/data/templates/.gitignore
autopilot/data/templates/tox.ini
autopilot/data/templates/CHANGES.rst
autopilot/data/templates/requirements.txt
autopilot/data/templates/tests/${project_name}_test.py
autopilot/data/templates/src/${project_name}/__init__.py
autopilot/data/templates/docs/Makefile
autopilot/data/templates/docs/source/index.rst
autopilot/data/templates/docs/source/intro.rst
autopilot/data/templates/docs/source/conf.py
autopilot/data/templates/docs/source/changelog.rst
